CHANGELOG.md
MANIFEST.in
README.md
setup.py
version.txt
deptools/__init__.py
deptools/changelogparser.py
deptools/createversionfile.py
deptools/deploy.py
deptools/register.py
deptools/runclangformat.py
deptools/spec.py
deptools/versiontype.py
deptools/windrvsign.py
deptools.egg-info/PKG-INFO
deptools.egg-info/SOURCES.txt
deptools.egg-info/dependency_links.txt
deptools.egg-info/entry_points.txt
deptools.egg-info/requires.txt
deptools.egg-info/top_level.txt
tests/__init__.py
tests/test_changelogparser.py
tests/test_deploy.py
tests/test_register.py
tests/test_versiontype.py