Metadata-Version: 2.1
Name: deptools
Version: 1.6.46
Summary: Application Deployment Tools
Home-page: https://alazartech.com
Author: Alazar Technologies
Author-email: support@alazartech.com
Classifier: Programming Language :: Python :: 3
Classifier: License :: OSI Approved :: MIT License
Classifier: Operating System :: OS Independent
Requires-Dist: docopt>=0.6.2
Requires-Dist: parsimonious>=0.8.1
Requires-Dist: pyminizip>=0.2.4
Requires-Dist: PyYAML>=5.1
Requires-Dist: azure-storage-blob>=12.5.0
Requires-Dist: node-semver>=0.6.1
